{
    "type": "FeatureCollection",
    "name": "noise_source_point_v2",
    "crs": {
        "type": "name",
        "properties": {
            "name": "urn:ogc:def:crs:OGC:1.3:CRS84"
        }
    },
    "features": [
        {
            "type": "Feature",
            "properties": {
                "source_noise_db": 90.0,
                "geometric_mean_freq_hz": 350.0
            },
            "geometry": {
                "type": "Point",
                "coordinates": [
                    30.728652268196306,
                    60.043648372143934
                ]
            }
        },
        {
            "type": "Feature",
            "properties": {
                "source_noise_db": 90.0,
                "geometric_mean_freq_hz": 350.0
            },
            "geometry": {
                "type": "Point",
                "coordinates": [
                    30.729395487536159,
                    60.044317419984424
                ]
            }
        },
        {
            "type": "Feature",
            "properties": {
                "source_noise_db": 90.0,
                "geometric_mean_freq_hz": 350.0
            },
            "geometry": {
                "type": "Point",
                "coordinates": [
                    30.730138706876016,
                    60.04498646782492
                ]
            }
        },
        {
            "type": "Feature",
            "properties": {
                "source_noise_db": 90.0,
                "geometric_mean_freq_hz": 350.0
            },
            "geometry": {
                "type": "Point",
                "coordinates": [
                    30.730881926215869,
                    60.045655515665409
                ]
            }
        },
        {
            "type": "Feature",
            "properties": {
                "source_noise_db": 90.0,
                "geometric_mean_freq_hz": 350.0
            },
            "geometry": {
                "type": "Point",
                "coordinates": [
                    30.731625145555721,
                    60.046324563505905
                ]
            }
        },
        {
            "type": "Feature",
            "properties": {
                "source_noise_db": 90.0,
                "geometric_mean_freq_hz": 350.0
            },
            "geometry": {
                "type": "Point",
                "coordinates": [
                    30.733098890488968,
                    60.046803221666551
                ]
            }
        },
        {
            "type": "Feature",
            "properties": {
                "source_noise_db": 90.0,
                "geometric_mean_freq_hz": 350.0
            },
            "geometry": {
                "type": "Point",
                "coordinates": [
                    30.733578010603697,
                    60.047449112138914
                ]
            }
        },
        {
            "type": "Feature",
            "properties": {
                "source_noise_db": 90.0,
                "geometric_mean_freq_hz": 350.0
            },
            "geometry": {
                "type": "Point",
                "coordinates": [
                    30.733854803575284,
                    60.04833170702738
                ]
            }
        },
        {
            "type": "Feature",
            "properties": {
                "source_noise_db": 90.0,
                "geometric_mean_freq_hz": 350.0
            },
            "geometry": {
                "type": "Point",
                "coordinates": [
                    30.734693169703259,
                    60.048856143839167
                ]
            }
        },
        {
            "type": "Feature",
            "properties": {
                "source_noise_db": 90.0,
                "geometric_mean_freq_hz": 350.0
            },
            "geometry": {
                "type": "Point",
                "coordinates": [
                    30.735451177115685,
                    60.049501015374041
                ]
            }
        },
        {
            "type": "Feature",
            "properties": {
                "source_noise_db": 90.0,
                "geometric_mean_freq_hz": 350.0
            },
            "geometry": {
                "type": "Point",
                "coordinates": [
                    30.736297532627827,
                    60.049736438064478
                ]
            }
        },
        {
            "type": "Feature",
            "properties": {
                "source_noise_db": 90.0,
                "geometric_mean_freq_hz": 350.0
            },
            "geometry": {
                "type": "Point",
                "coordinates": [
                    30.737264400215984,
                    60.04948115965378
                ]
            }
        }
    ]
}